MatlabBlenderIO/__init__.py
MatlabBlenderIO/body.m
MatlabBlenderIO/csv2obj.m
MatlabBlenderIO/csv2obj.py
MatlabBlenderIO/csvtext2matrix.m
MatlabBlenderIO/csvtext2matrix.py
MatlabBlenderIO/draw_obj.m
MatlabBlenderIO/filename2varname.m
MatlabBlenderIO/matrix2csvtext.m
MatlabBlenderIO/matrix2csvtext.py
MatlabBlenderIO/obj2csv.m
MatlabBlenderIO/obj2csv.py
MatlabBlenderIO/query_csv.m
MatlabBlenderIO/query_csv.py
MatlabBlenderIO-0.0.6.dist-info/LICENSE
MatlabBlenderIO-0.0.6.dist-info/METADATA
MatlabBlenderIO-0.0.6.dist-info/WHEEL
MatlabBlenderIO-0.0.6.dist-info/top_level.txt
MatlabBlenderIO-0.0.6.dist-info/RECORD
