Metadata-Version: 2.1
Name: MatlabBlenderIO
Version: 0.0.6
Summary: A solution for transferring data in and out of Blender and MATLAB, for example for ODE-solvers etc.
Home-page: https://github.com/spiggen/MatlabBlenderIO
Author: Vilgot Lötberg
Author-email: vilgotl@kth.se
Requires-Python: >=3.6
License-File: LICENSE
